setup.py
elly/__init__.py
elly/count_down_latch.py
elly/decorator.py
elly/exception_ignore.py
elly/util.py
elly.egg-info/PKG-INFO
elly.egg-info/SOURCES.txt
elly.egg-info/dependency_links.txt
elly.egg-info/top_level.txt